CHANGELOG.txt
LICENSE.txt
MANIFEST.in
README.txt
runtests.py
setup.py
Yapsy.egg-info/PKG-INFO
Yapsy.egg-info/SOURCES.txt
Yapsy.egg-info/dependency_links.txt
Yapsy.egg-info/top_level.txt
artwork/LICENSE.txt
artwork/yapsy-big.png
artwork/yapsy-favicon.ico
artwork/yapsy-favicon.png
artwork/yapsy.png
artwork/yapsy.svg
doc/Advices.rst
doc/AutoInstallPluginManager.rst
doc/ConfigurablePluginManager.rst
doc/Extensions.rst
doc/FilteredPluginManager.rst
doc/IMultiprocessChildPlugin.rst
doc/IPlugin.rst
doc/IPluginLocator.rst
doc/Makefile
doc/MultiprocessPluginManager.rst
doc/MultiprocessPluginProxy.rst
doc/PluginFileLocator.rst
doc/PluginInfo.rst
doc/PluginManager.rst
doc/PluginManagerDecorator.rst
doc/VersionedPluginManager.rst
doc/conf.py
doc/index.rst
doc/make.bat
test/__init__.py
test/test_All.py
test/test_AutoInstallPlugin.py
test/test_ConfigPlugin.py
test/test_ErrorInPlugin.py
test/test_FilterPlugin.py
test/test_PluginFileLocator.py
test/test_PluginInfo.py
test/test_SimpleMultiprocessPlugin.py
test/test_SimplePlugin.py
test/test_Singleton.py
test/test_VersionedPlugin.py
test/test_settings.py
test/plugins/ConfigPlugin.py
test/plugins/ErroneousPlugin.py
test/plugins/LegacyMultiprocessPlugin.py
test/plugins/SimpleMultiprocessPlugin.py
test/plugins/SimplePlugin.py
test/plugins/VersionedPlugin10.py
test/plugins/VersionedPlugin11.py
test/plugins/VersionedPlugin111.py
test/plugins/VersionedPlugin12.py
test/plugins/VersionedPlugin12a1.py
test/plugins/configplugin.yapsy-config-plugin
test/plugins/configplugin.yapsy-filter-plugin
test/plugins/erroneousplugin.yapsy-error-plugin
test/plugins/legacymultiprocessplugin.multiprocess-plugin
test/plugins/simplemultiprocessplugin.multiprocess-plugin
test/plugins/simpleplugin.yapsy-filter-plugin
test/plugins/simpleplugin.yapsy-plugin
test/plugins/versioned10.version-plugin
test/plugins/versioned11.version-plugin
test/plugins/versioned111.version-plugin
test/plugins/versioned12.version-plugin
test/plugins/versioned12a1.version-plugin
test/pluginsasdirs/simpleplugin.yapsy-plugin
test/pluginsasdirs/SimplePlugin/__init__.py
