Metadata-Version: 1.1
Name: Yapsy
Version: 1.12.1
Summary: Yet another plugin system
Home-page: http://yapsy.sourceforge.net
Author: Thibauld Nion
Author-email: thibauld@tibonihoo.net
License: BSD
Keywords: plugin manager
Platform: All
Classifier: Development Status :: 5 - Production/Stable
Classifier: Intended Audience :: Developers
Classifier: License :: OSI Approved :: BSD License
Classifier: Operating System :: OS Independent
Classifier: Programming Language :: Python
Classifier: Programming Language :: Python :: 2
Classifier: Programming Language :: Python :: 3
Classifier: Topic :: Software Development :: Libraries :: Python Modules
